tests/__init__.py
tests/numpy/__init__.py
tests/numpy/test_stats_running.py
tests/numpy/test_variance.py
tests/pytorch/__init__.py
tests/pytorch/test_stats_running.py
tmeasures/__init__.py
tmeasures/adapters.py
tmeasures/measure.py
tmeasures/transformation.py
tmeasures/np/__init__.py
tmeasures/np/activations_iterator.py
tmeasures/np/aggregation.py
tmeasures/np/anova.py
tmeasures/np/base.py
tmeasures/np/distance_invariance.py
tmeasures/np/distance_same_equivariance.py
tmeasures/np/goodfellow.py
tmeasures/np/goodfellow_prob.py
tmeasures/np/layer_transformation.py
tmeasures/np/quotient.py
tmeasures/np/same_equivariance_simple.py
tmeasures/np/stats_running.py
tmeasures/np/variance_invariance.py
tmeasures/np/variance_same_equivariance.py
tmeasures/np/multithread/__init__.py
tmeasures/np/multithread/event_driven_layer_measure.py
tmeasures/np/multithread/functions.py
tmeasures/np/multithread/goodfellow_prob_multithreaded.py
tmeasures/np/multithread/multithreaded_layer_measure.py
tmeasures/np/multithread/multithreaded_variance.py
tmeasures/pytorch/__init__.py
tmeasures/pytorch/activations_iterator.py
tmeasures/pytorch/activations_iterator_base.py
tmeasures/pytorch/activations_transformer.py
tmeasures/pytorch/base.py
tmeasures/pytorch/dataset2d.py
tmeasures/pytorch/goodfellow.py
tmeasures/pytorch/layer_measures.py
tmeasures/pytorch/measure_transformer.py
tmeasures/pytorch/model.py
tmeasures/pytorch/quotient.py
tmeasures/pytorch/stats_running.py
tmeasures/pytorch/util.py
tmeasures/pytorch/variance_invariance.py
tmeasures/pytorch/variance_sameequivariance.py
tmeasures/pytorch/transformations/__init__.py
tmeasures/pytorch/transformations/affine.py
tmeasures/transformations/__init__.py
tmeasures/transformations/affine.py
tmeasures/transformations/parameters.py
tmeasures/transformations/numpy/__init__.py
tmeasures/transformations/numpy/affine.py
tmeasures/utils/__init__.py
tmeasures/utils/iterable_queue.py
tmeasures/visualization/__init__.py
tmeasures/visualization/features.py
tmeasures-1.2.11.dist-info/LICENSE
tmeasures-1.2.11.dist-info/METADATA
tmeasures-1.2.11.dist-info/WHEEL
tmeasures-1.2.11.dist-info/top_level.txt
tmeasures-1.2.11.dist-info/zip-safe
tmeasures-1.2.11.dist-info/RECORD
