Metadata-Version: 2.1
Name: tmeasures
Version: 1.2.11
Summary: Invariance, Same-Equivariance and other measures for Neural Networks. Support for PyTorch (now) and TensorFlow (coming).
Home-page: https://github.com/facundoq/tmeasures
Author: Facundo Manuel Quiroga
Author-email: facundoq@gmail.com
Project-URL: Bug Tracker, https://github.com/facundoq/tmeasures/issues
Project-URL: Documentation, https://github.com/facundoq/tmeasures
Project-URL: Source Code, https://github.com/facundoq/tmeasures
Keywords: transformational measures equivariance same-equivariance invariance variance neural networks python pytorch numpy tensorflow
Classifier: License :: OSI Approved :: Python Software Foundation License
Classifier: License :: OSI Approved :: GNU Affero General Public License v3 or later (AGPLv3+)
Classifier: Development Status :: 4 - Beta
Classifier: Topic :: Scientific/Engineering :: Artificial Intelligence
Classifier: Topic :: Scientific/Engineering :: Visualization
Requires-Python: >=3.6
License-File: LICENSE
Requires-Dist: numpy
Requires-Dist: scipy
Requires-Dist: matplotlib
Requires-Dist: data-science-types
Requires-Dist: tqdm
Requires-Dist: opencv-python
Requires-Dist: scikit-image
